cheaders/__init__.py
cheaders/__main__.py
cheaders-1.0.0.dist-info/DESCRIPTION.rst
cheaders-1.0.0.dist-info/METADATA
cheaders-1.0.0.dist-info/RECORD
cheaders-1.0.0.dist-info/WHEEL
cheaders-1.0.0.dist-info/metadata.json
cheaders-1.0.0.dist-info/top_level.txt
